toastapi/__init__.py
toastapi/api_client.py
toastapi/api_response.py
toastapi/configuration.py
toastapi/exceptions.py
toastapi/py.typed
toastapi/rest.py
toastapi/api/__init__.py
toastapi/api/alternate_payment_types_api.py
toastapi/api/analytics_api.py
toastapi/api/authentication_api.py
toastapi/api/break_types_api.py
toastapi/api/cash_drawers_api.py
toastapi/api/dining_options_api.py
toastapi/api/discounts_api.py
toastapi/api/employees_api.py
toastapi/api/jobs_api.py
toastapi/api/menu_groups_api.py
toastapi/api/menu_items_api.py
toastapi/api/menus_v2_api.py
toastapi/api/menus_v3_api.py
toastapi/api/modifier_groups_api.py
toastapi/api/no_sale_reasons_api.py
toastapi/api/orders_api.py
toastapi/api/payments_api.py
toastapi/api/payout_reasons_api.py
toastapi/api/pre_modifier_groups_api.py
toastapi/api/pre_modifiers_api.py
toastapi/api/price_groups_api.py
toastapi/api/printers_api.py
toastapi/api/restaurant_services_api.py
toastapi/api/restaurants_api.py
toastapi/api/revenue_centers_api.py
toastapi/api/sales_categories_api.py
toastapi/api/service_areas_api.py
toastapi/api/service_charges_api.py
toastapi/api/shifts_api.py
toastapi/api/tables_api.py
toastapi/api/tax_rates_api.py
toastapi/api/time_entries_api.py
toastapi/api/tip_withholding_api.py
toastapi/api/void_reasons_api.py
toastapi/models/__init__.py
toastapi/models/alcohol.py
toastapi/models/alternate_payment_type.py
toastapi/models/applicable_discount.py
toastapi/models/applicable_discounts_request.py
toastapi/models/applied_discount.py
toastapi/models/applied_discount_reason.py
toastapi/models/applied_discount_trigger.py
toastapi/models/applied_loyalty_info.py
toastapi/models/applied_packaging_info.py
toastapi/models/applied_packaging_item.py
toastapi/models/applied_service_charge.py
toastapi/models/applied_tax_rate.py
toastapi/models/authentication_request.py
toastapi/models/authentication_response.py
toastapi/models/authentication_token.py
toastapi/models/availability.py
toastapi/models/break_type.py
toastapi-1.1.2.dist-info/licenses/LICENSE
toastapi-1.1.2.dist-info/METADATA
toastapi-1.1.2.dist-info/WHEEL
toastapi-1.1.2.dist-info/top_level.txt
toastapi-1.1.2.dist-info/RECORD
