Metadata-Version: 2.4
Name: toastapi
Version: 1.1.2
Summary: Toast API
Home-page: https://github.com/growth-operations/toast
Author: Growth Operations support
Author-email: Growth Operations support <info@growthoperationsco.com>
License: MIT
Project-URL: Repository, https://github.com/growth-operations/toast
Keywords: OpenAPI,OpenAPI-Generator,Toast API
Requires-Python: >=3.9
License-File: LICENSE
Requires-Dist: urllib3<3.0.0,>=2.1.0
Requires-Dist: python-dateutil>=2.8.2
Requires-Dist: aiohttp>=3.8.4
Requires-Dist: aiohttp-retry>=2.8.3
Requires-Dist: pydantic>=2
Requires-Dist: typing-extensions>=4.7.1
Dynamic: author
Dynamic: home-page
Dynamic: license-file
